gosms_ru_client/__init__.py
gosms_ru_client/client.py
gosms_ru_client/exceptions.py
gosms_ru_client-0.1.6.dist-info/licenses/LICENSE
gosms_ru_client-0.1.6.dist-info/METADATA
gosms_ru_client-0.1.6.dist-info/WHEEL
gosms_ru_client-0.1.6.dist-info/top_level.txt
gosms_ru_client-0.1.6.dist-info/RECORD
