Metadata-Version: 2.4
Name: gosms-ru-client
Version: 0.1.6
Summary: Python SDK для работы с API GoSMS
Author-email: GoSMS Project <support@gosms.ru>
Project-URL: Homepage, https://github.com/Gosms-ru/python-sdk
Project-URL: Documentation, https://docs.gosms.ru/
Classifier: Programming Language :: Python :: 3
Classifier: License :: OSI Approved :: MIT License
Classifier: Operating System :: OS Independent
Requires-Python: >=3.7
License-File: LICENSE
Requires-Dist: requests>=2.25.0
Dynamic: license-file
